sqlite3cm/__init__.py
sqlite3cm/sqlite3cm.py
sqlite3cm-0.0.3.dist-info/METADATA
sqlite3cm-0.0.3.dist-info/WHEEL
sqlite3cm-0.0.3.dist-info/top_level.txt
sqlite3cm-0.0.3.dist-info/RECORD
