Metadata-Version: 2.1
Name: sqlite3cm
Version: 0.0.3
Summary: Context manager for Sqlite databases
Home-page: https://github.com/ahmedlahrizi/sqlite3_CM
Author: Ahmed LAHRIZI
License: UNKNOWN
Keywords: python,sql,sqlite,3,cm,context,manage,database,db
Platform: UNKNOWN
Classifier: Programming Language :: Python :: 3
Classifier: License :: OSI Approved :: MIT License
Classifier: Operating System :: OS Independent
